pydoge_oracle/__init__.py
pydoge_oracle/oracle_client.py
PyDoge_oracle-0.1.3.dist-info/LICENSE
PyDoge_oracle-0.1.3.dist-info/METADATA
PyDoge_oracle-0.1.3.dist-info/WHEEL
PyDoge_oracle-0.1.3.dist-info/top_level.txt
PyDoge_oracle-0.1.3.dist-info/RECORD
