Metadata-Version: 2.1
Name: PyDoge-oracle
Version: 0.1.3
Summary: An oracle library
Home-page: https://github.com/ezeportela/pydoge-oracle
Author: Ezequiel Portela
Author-email: eportelab@gmail.com
License: UNKNOWN
Platform: UNKNOWN
Classifier: Programming Language :: Python :: 3
Classifier: License :: OSI Approved :: MIT License
Classifier: Operating System :: OS Independent
Requires-Python: >=3.6
Requires-Dist: PyDoge
Requires-Dist: cx-Oracle
